pimemory-0.0.2.dist-info/licenses/LICENSE
proj/__init__.py
proj/main.py
pimemory-0.0.2.dist-info/METADATA
pimemory-0.0.2.dist-info/WHEEL
pimemory-0.0.2.dist-info/top_level.txt
pimemory-0.0.2.dist-info/RECORD
