Metadata-Version: 2.4
Name: PiMemory
Version: 0.0.2
Summary: performs a calculation passed through to it
Author-email: Arvin <arvin052006@gmail.com>
License-File: LICENSE
Dynamic: license-file
